LICENSE.md
MANIFEST.in
README.md
setup.py
netviel/__init__.py
netviel/__main__.py
netviel/api.py
netviel/wsgi.py
netviel.egg-info/PKG-INFO
netviel.egg-info/SOURCES.txt
netviel.egg-info/dependency_links.txt
netviel.egg-info/requires.txt
netviel.egg-info/top_level.txt
netviel/js/index.html
netviel/js/net-viel.js
netviel/js/net-viel.js.map
netviel/js/polyfills/custom-elements-es5-adapter.84b300ee818dce8b351c7cc7c100bcf7.js
netviel/js/polyfills/custom-elements-es5-adapter.84b300ee818dce8b351c7cc7c100bcf7.js.map
netviel/js/polyfills/dynamic-import.b745cfc9384367cc18b42bbef2bbdcd9.js
netviel/js/polyfills/dynamic-import.b745cfc9384367cc18b42bbef2bbdcd9.js.map
netviel/js/polyfills/webcomponents.cc3976af76b5e726e2a7e86686c930f1.js
netviel/js/polyfills/webcomponents.cc3976af76b5e726e2a7e86686c930f1.js.map