Metadata-Version: 2.1
Name: netviel
Version: 0.2.1
Home-page: https://github.com/DavidMStraub/netviel
Author: David M. Straub <straub@protonmail.com>
Author-email: straub@protonmail.com
License: MIT
License-File: LICENSE.md
